{
	"format_version": "1.8.0",
	"animations": {
		"animation.no_bedrock_bridging.dialogue_entity": {
			"loop": true,
			"animation_length": 7,
			"bones": {
				"bone2": {
					"scale": {
						"0.5": [0.2, 0.2, 0.2],
						"1.125": [0.2, 0.2, 0.2],
						"2.0": [0.2, 0.2, 0.2],
						"2.25": [1.2, 1.2, 1.2],
						"3.25": [1.2, 1.2, 1.2],
						"3.2917": [0, 0, 0]
					}
				},
				"waist": {
					"rotation": {
						"3.75": [0, 0, 0],
						"4.25": [0, 180, 0]
					}
				},
				"body": {
					"rotation": {
						"4.25": [0, 0, 0],
						"4.75": [40, 0, 0]
					}
				},
				"head": {
					"rotation": {
						"4.25": [0, 0, 0],
						"4.75": [45, 0, 0]
					}
				},
				"rightArm": {
					"rotation": {
						"0.5": [0, 0, 0],
						"1.0": [-40, 0, 0],
						"3.25": [-40, 0, 0],
						"3.2917": [0, 0, 0],
						"4.75": [0, 0, 0],
						"5.25": [-45, 0, 0]
					}
				},
				"bone": {
					"rotation": [0, 0, 0]
				},
				"bone3": {
					"rotation": {
						"1.25": [0, 0, 0],
						"1.5": [-50, 0, 0],
						"3.25": [-50, 0, 0],
						"3.2917": [0, 0, 0],
						"5.5": [0, 0, 0],
						"5.75": [-85, 0, 0]
					},
					"position": {
						"1.25": [0, 0, 0],
						"1.5": [11, -8, 54],
						"3.25": [11, -8, 54],
						"3.2917": [0, 0, 0],
						"5.5": [0, 0, 0],
						"5.75": [11, -34, 60]
					},
					"scale": {
						"0.5": [0.2, 0.2, 0.2],
						"1.25": [0.2, 0.2, 0.2],
						"1.5": [1, 1, 1],
						"3.25": [1, 1, 1],
						"3.2917": [0.2, 0.2, 0.2],
						"5.5": [0.2, 0.2, 0.2],
						"5.75": [1, 1, 1]
					}
				}
			}
		}
	}
}